vhpy/VH.py
vhpy/__init__.py
vhpy/constants.py
vhpy-0.1.3.dist-info/WHEEL
vhpy-0.1.3.dist-info/METADATA
vhpy-0.1.3.dist-info/LICENSE.md
vhpy-0.1.3.dist-info/RECORD
