Metadata-Version: 2.1
Name: vhpy
Version: 0.1.3
Summary: V&H (or 'V and H' or 'VH') Coordinates in Python
Home-page: https://github.com/kurtabersold/vhpy
License: MIT
Author: Paul Pomerleau
Maintainer: Kurt Abersold
Maintainer-email: kurtabersold@gmail.com
Requires-Python: >=3.8,<4.0
Classifier: Intended Audience :: Telecommunications Industry
Classifier: License :: OSI Approved :: MIT License
Classifier: Programming Language :: Python :: 3
Classifier: Programming Language :: Python :: 3.8
Classifier: Programming Language :: Python :: 3.9
Classifier: Programming Language :: Python :: 3.10
Classifier: Programming Language :: Python :: 3.11
Classifier: Topic :: Communications :: Telephony
Project-URL: Repository, https://github.com/kurtabersold/vhpy
